configuration/__init__.py
configuration/configuration.py
connectors/__init__.py
connectors/aoai.py
connectors/cosmosdb.py
tools/__init__.py
gpt_rag_common-0.0.1.dist-info/METADATA
gpt_rag_common-0.0.1.dist-info/WHEEL
gpt_rag_common-0.0.1.dist-info/top_level.txt
gpt_rag_common-0.0.1.dist-info/RECORD
